noodleExtensions/__init__.py
noodleExtensions/events.py
noodleExtensions/objects.py
NoodleExtensions-2.1.0.dist-info/LICENSE
NoodleExtensions-2.1.0.dist-info/METADATA
NoodleExtensions-2.1.0.dist-info/WHEEL
NoodleExtensions-2.1.0.dist-info/top_level.txt
NoodleExtensions-2.1.0.dist-info/RECORD
