Metadata-Version: 2.1
Name: NoodleExtensions
Version: 2.1.0
Summary: Edit Beat Saber Noodle Extensions level easily using this library.
Home-page: https://github.com/megamaz/NoodleExtensions-python
Author: megamaz
Author-email: raphael.mazuel@gmail.com
License: MIT license
Project-URL: Bug Reports, https://github.com/megamaz/NoodleExtensions-python/issues
Keywords: Beat Saber,Noodle Extensions
Platform: UNKNOWN
Classifier: Development Status :: 4 - Beta
Classifier: Programming Language :: Python :: 3.9
Requires-Python: >=3.8, <4
